Metadata-Version: 1.0
Name: xmlsq
Version: 0.9.0a0
Summary: A Python interface to xmlsq.
Home-page: https://www.cryptosys.net/xmlsq/
Author: David Ireland
Author-email: UNKNOWN
License: UNKNOWN
Platform: Windows
